[
	{
		"fideid": 22022996,
		"name": "Lefebvre, Aurelien Tegawende",
		"country": "BUR",
		"sex": "M",
		"title": "",
		"w_title": "",
		"o_title": "",
		"foa_title": "",
		"games": 0,
		"k": 40,
		"birthday": 1995,
		"flag": "",
		"rating_standard": 1786,
		"rating_rapid": null,
		"rating_blitz": null
	},
	{
		"fideid": 22004670,
		"name": "Zabramba, Joachim",
		"country": "BUR",
		"sex": "M",
		"title": "",
		"w_title": "",
		"o_title": "",
		"foa_title": "",
		"games": 0,
		"k": 40,
		"birthday": 1946,
		"flag": "i",
		"rating_standard": 1775,
		"rating_rapid": null,
		"rating_blitz": null
	},
	{
		"fideid": 22003355,
		"name": "Koita Idrissa",
		"country": "BUR",
		"sex": "M",
		"title": "",
		"w_title": "",
		"o_title": "",
		"foa_title": "",
		"games": 0,
		"k": 20,
		"birthday": 1971,
		"flag": "i",
		"rating_standard": 1768,
		"rating_rapid": 1788,
		"rating_blitz": 1811
	},
	{
		"fideid": 22003266,
		"name": "Carbonell, Nicolas",
		"country": "BUR",
		"sex": "M",
		"title": "",
		"w_title": "",
		"o_title": "",
		"foa_title": "",
		"games": 0,
		"k": 20,
		"birthday": 1965,
		"flag": "",
		"rating_standard": 1758,
		"rating_rapid": 1839,
		"rating_blitz": 1843
	},
	{
		"fideid": 22006095,
		"name": "Koita, Saidou",
		"country": "BUR",
		"sex": "M",
		"title": "",
		"w_title": "",
		"o_title": "",
		"foa_title": "",
		"games": 0,
		"k": 40,
		"birthday": 1973,
		"flag": "i",
		"rating_standard": 1743,
		"rating_rapid": 1751,
		"rating_blitz": 1723
	},
	{
		"fideid": 22004548,
		"name": "Briba, Oumar",
		"country": "BUR",
		"sex": "M",
		"title": "",
		"w_title": "",
		"o_title": "",
		"foa_title": "",
		"games": 0,
		"k": 40,
		"birthday": 1963,
		"flag": "i",
		"rating_standard": 1729,
		"rating_rapid": null,
		"rating_blitz": null
	},
	{
		"fideid": 22003339,
		"name": "Jeroui Toufik",
		"country": "BUR",
		"sex": "M",
		"title": "",
		"w_title": "",
		"o_title": "",
		"foa_title": "",
		"games": 0,
		"k": 40,
		"birthday": 1965,
		"flag": "i",
		"rating_standard": 1714,
		"rating_rapid": null,
		"rating_blitz": null
	},
	{
		"fideid": 22003282,
		"name": "Guissou, Clement",
		"country": "BUR",
		"sex": "M",
		"title": "",
		"w_title": "",
		"o_title": "",
		"foa_title": "",
		"games": 0,
		"k": 40,
		"birthday": 1959,
		"flag": "i",
		"rating_standard": 1713,
		"rating_rapid": 1653,
		"rating_blitz": 1653
	},
	{
		"fideid": 22007733,
		"name": "KOITA SEYDOU",
		"country": "BUR",
		"sex": "M",
		"title": "",
		"w_title": "",
		"o_title": "",
		"foa_title": "",
		"games": 0,
		"k": 40,
		"birthday": 1973,
		"flag": "i",
		"rating_standard": 1697,
		"rating_rapid": null,
		"rating_blitz": null
	},
	{
		"fideid": 22003320,
		"name": "Bouda Robert",
		"country": "BUR",
		"sex": "M",
		"title": "",
		"w_title": "",
		"o_title": "SI",
		"foa_title": "",
		"games": 0,
		"k": 40,
		"birthday": 1982,
		"flag": "i",
		"rating_standard": 1683,
		"rating_rapid": null,
		"rating_blitz": null
	},
	{
		"fideid": 22003312,
		"name": "Kiema Wend Nonga Raoul Frederic",
		"country": "BUR",
		"sex": "M",
		"title": "",
		"w_title": "",
		"o_title": "",
		"foa_title": "",
		"games": 0,
		"k": 40,
		"birthday": 1980,
		"flag": "i",
		"rating_standard": 1643,
		"rating_rapid": 1604,
		"rating_blitz": 1605
	},
	{
		"fideid": 22003290,
		"name": "binah lionel bina",
		"country": "BUR",
		"sex": "M",
		"title": "",
		"w_title": "",
		"o_title": "",
		"foa_title": "",
		"games": 0,
		"k": 40,
		"birthday": 1982,
		"flag": "i",
		"rating_standard": 1609,
		"rating_rapid": null,
		"rating_blitz": null
	},
	{
		"fideid": 22000160,
		"name": "Guene, Herve Jean Louis",
		"country": "BUR",
		"sex": "M",
		"title": "",
		"w_title": "",
		"o_title": "",
		"foa_title": "",
		"games": 0,
		"k": 40,
		"birthday": 1984,
		"flag": "i",
		"rating_standard": 1609,
		"rating_rapid": null,
		"rating_blitz": null
	},
	{
		"fideid": 22003274,
		"name": "koita abdoulaye adama",
		"country": "BUR",
		"sex": "M",
		"title": "",
		"w_title": "",
		"o_title": "",
		"foa_title": "",
		"games": 0,
		"k": 40,
		"birthday": 1944,
		"flag": "i",
		"rating_standard": 1609,
		"rating_rapid": null,
		"rating_blitz": null
	},
	{
		"fideid": 22000135,
		"name": "Ouedraogo S Arnaud J D",
		"country": "BUR",
		"sex": "M",
		"title": "",
		"w_title": "",
		"o_title": "SI,SI",
		"foa_title": "",
		"games": 0,
		"k": 40,
		"birthday": 1983,
		"flag": "i",
		"rating_standard": 1597,
		"rating_rapid": null,
		"rating_blitz": null
	},
	{
		"fideid": 22000178,
		"name": "Mevi, Herve Stephane",
		"country": "BUR",
		"sex": "M",
		"title": "",
		"w_title": "",
		"o_title": "",
		"foa_title": "",
		"games": 0,
		"k": 40,
		"birthday": 1974,
		"flag": "i",
		"rating_standard": 1591,
		"rating_rapid": null,
		"rating_blitz": null
	},
	{
		"fideid": 22028390,
		"name": "Lompo, Boammani Aser",
		"country": "BUR",
		"sex": "M",
		"title": "",
		"w_title": "",
		"o_title": "",
		"foa_title": "",
		"games": 0,
		"k": 40,
		"birthday": 1997,
		"flag": "",
		"rating_standard": 1529,
		"rating_rapid": null,
		"rating_blitz": 1562
	},
	{
		"fideid": 652066010,
		"name": "Sanou, Edmond",
		"country": "BUR",
		"sex": "M",
		"title": "",
		"w_title": "",
		"o_title": "",
		"foa_title": "",
		"games": 0,
		"k": 20,
		"birthday": 1996,
		"flag": "",
		"rating_standard": null,
		"rating_rapid": 1538,
		"rating_blitz": null
	}
]
